adaptwms/__init__.py
adaptwms/admin.py
adaptwms/apps.py
adaptwms/migrations/__init__.py
adaptwms/models.py
adaptwms/templates/pages/interface.html
adaptwms/templates/template.html
adaptwms/tests.py
adaptwms/translator.py
adaptwms/views.py
adaptwms-0.1.2.dist-info/LICENSE
adaptwms-0.1.2.dist-info/METADATA
adaptwms-0.1.2.dist-info/WHEEL
adaptwms-0.1.2.dist-info/RECORD
