Metadata-Version: 2.1
Name: adaptwms
Version: 0.1.2
Summary: Lightweight OpenStreetMap adapter for WMS services as Django app
Home-page: https://github.com/v3l0c1r4pt0r/adaptwms
Author: v3l0c1r4pt0r
Author-email: v3l0c1r4pt0r@gmail.com
Requires-Python: >=3.11,<4.0
Classifier: Framework :: Django
Classifier: Programming Language :: Python :: 3
Classifier: Programming Language :: Python :: 3.11
Requires-Dist: django (>=4.2.2,<5.0.0)
Requires-Dist: pyproj (>=3.6.0,<4.0.0)
Requires-Dist: requests (>=2.31.0,<3.0.0)
Project-URL: Repository, https://github.com/v3l0c1r4pt0r/adaptwms
